cloudwatchpy/__init__.py
cloudwatchpy/batcher.py
cloudwatchpy/client.py
cloudwatchpy/compressor.py
cloudwatchpy/config.py
cloudwatchpy/exceptions.py
cloudwatchpy/fallback_logger.py
cloudwatchpy/logger.py
cloudwatchpy/middleware.py
cloudwatchpy/models.py
cloudwatchpy/utils.py
cloudwatchpy-0.0.2.dist-info/METADATA
cloudwatchpy-0.0.2.dist-info/WHEEL
cloudwatchpy-0.0.2.dist-info/RECORD
