Metadata-Version: 2.4
Name: cloudwatchpy
Version: 0.0.2
Summary: Structured Python logger for AWS CloudWatch with ASGI/WSGI middleware support and fallback local logging
Project-URL: Repository, https://github.com/irfan-ahmad-byte/cloudwatchpy
Author: Irfan Ahmad
License-Expression: MIT
Keywords: AWS,AWS logger,CloudWatch,CloudWatchLogs,Cloudwatch logger,Python logger,logger
Requires-Python: >=3.9
Requires-Dist: aiohttp>=3.9.0
Requires-Dist: boto3>=1.34.0
Requires-Dist: python-dotenv>=1.0.0
